[
    {
        "subject": "Environmental Engineering",
        "subcategory": "Sources & Demand of water",
        "type": "Theory-based MCQ",
        "question": "Sample placeholder question for Sources & Demand of water.",
        "options": {
            "a": "True",
            "b": "False",
            "c": "Maybe",
            "d": "None"
        },
        "correct_answer": "a",
        "explanation": "This is a system-generated placeholder to prevent app crash on empty subcategories."
    },
    {
        "subject": "Environmental Engineering",
        "subcategory": "Sources & Demand of water",
        "type": "Theory-based MCQ",
        "question": "Sample placeholder question for Sources & Demand of water. [Set Variant 1]",
        "options": {
            "a": "True",
            "b": "False",
            "c": "Maybe",
            "d": "None"
        },
        "correct_answer": "a",
        "explanation": "This is a system-generated placeholder to prevent app crash on empty subcategories."
    },
    {
        "subject": "Environmental Engineering",
        "subcategory": "Sources & Demand of water",
        "type": "Theory-based MCQ",
        "question": "Sample placeholder question for Sources & Demand of water. [Set Variant 2]",
        "options": {
            "a": "True",
            "b": "False",
            "c": "Maybe",
            "d": "None"
        },
        "correct_answer": "a",
        "explanation": "This is a system-generated placeholder to prevent app crash on empty subcategories."
    },
    {
        "subject": "Environmental Engineering",
        "subcategory": "Sources & Demand of water",
        "type": "Theory-based MCQ",
        "question": "Sample placeholder question for Sources & Demand of water. [Set Variant 3]",
        "options": {
            "a": "True",
            "b": "False",
            "c": "Maybe",
            "d": "None"
        },
        "correct_answer": "a",
        "explanation": "This is a system-generated placeholder to prevent app crash on empty subcategories."
    },
    {
        "subject": "Environmental Engineering",
        "subcategory": "Sources & Demand of water",
        "type": "Theory-based MCQ",
        "question": "Sample placeholder question for Sources & Demand of water. [Set Variant 4]",
        "options": {
            "a": "True",
            "b": "False",
            "c": "Maybe",
            "d": "None"
        },
        "correct_answer": "a",
        "explanation": "This is a system-generated placeholder to prevent app crash on empty subcategories."
    },
    {
        "subject": "Environmental Engineering",
        "subcategory": "Sources & Demand of water",
        "type": "Theory-based MCQ",
        "question": "Sample placeholder question for Sources & Demand of water. [Set Variant 5]",
        "options": {
            "a": "True",
            "b": "False",
            "c": "Maybe",
            "d": "None"
        },
        "correct_answer": "a",
        "explanation": "This is a system-generated placeholder to prevent app crash on empty subcategories."
    },
    {
        "subject": "Environmental Engineering",
        "subcategory": "Sources & Demand of water",
        "type": "Theory-based MCQ",
        "question": "Sample placeholder question for Sources & Demand of water. [Set Variant 6]",
        "options": {
            "a": "True",
            "b": "False",
            "c": "Maybe",
            "d": "None"
        },
        "correct_answer": "a",
        "explanation": "This is a system-generated placeholder to prevent app crash on empty subcategories."
    },
    {
        "subject": "Environmental Engineering",
        "subcategory": "Sources & Demand of water",
        "type": "Theory-based MCQ",
        "question": "Sample placeholder question for Sources & Demand of water. [Set Variant 7]",
        "options": {
            "a": "True",
            "b": "False",
            "c": "Maybe",
            "d": "None"
        },
        "correct_answer": "a",
        "explanation": "This is a system-generated placeholder to prevent app crash on empty subcategories."
    },
    {
        "subject": "Environmental Engineering",
        "subcategory": "Sources & Demand of water",
        "type": "Theory-based MCQ",
        "question": "Sample placeholder question for Sources & Demand of water. [Set Variant 8]",
        "options": {
            "a": "True",
            "b": "False",
            "c": "Maybe",
            "d": "None"
        },
        "correct_answer": "a",
        "explanation": "This is a system-generated placeholder to prevent app crash on empty subcategories."
    },
    {
        "subject": "Environmental Engineering",
        "subcategory": "Sources & Demand of water",
        "type": "Theory-based MCQ",
        "question": "Sample placeholder question for Sources & Demand of water. [Set Variant 9]",
        "options": {
            "a": "True",
            "b": "False",
            "c": "Maybe",
            "d": "None"
        },
        "correct_answer": "a",
        "explanation": "This is a system-generated placeholder to prevent app crash on empty subcategories."
    },
    {
        "subject": "Environmental Engineering",
        "subcategory": "Sources & Demand of water",
        "type": "Theory-based MCQ",
        "question": "Sample placeholder question for Sources & Demand of water. [Set Variant 10]",
        "options": {
            "a": "True",
            "b": "False",
            "c": "Maybe",
            "d": "None"
        },
        "correct_answer": "a",
        "explanation": "This is a system-generated placeholder to prevent app crash on empty subcategories."
    },
    {
        "subject": "Environmental Engineering",
        "subcategory": "Sources & Demand of water",
        "type": "Theory-based MCQ",
        "question": "Sample placeholder question for Sources & Demand of water. [Set Variant 11]",
        "options": {
            "a": "True",
            "b": "False",
            "c": "Maybe",
            "d": "None"
        },
        "correct_answer": "a",
        "explanation": "This is a system-generated placeholder to prevent app crash on empty subcategories."
    },
    {
        "subject": "Environmental Engineering",
        "subcategory": "Sources & Demand of water",
        "type": "Theory-based MCQ",
        "question": "Sample placeholder question for Sources & Demand of water. [Set Variant 12]",
        "options": {
            "a": "True",
            "b": "False",
            "c": "Maybe",
            "d": "None"
        },
        "correct_answer": "a",
        "explanation": "This is a system-generated placeholder to prevent app crash on empty subcategories."
    },
    {
        "subject": "Environmental Engineering",
        "subcategory": "Sources & Demand of water",
        "type": "Theory-based MCQ",
        "question": "Sample placeholder question for Sources & Demand of water. [Set Variant 13]",
        "options": {
            "a": "True",
            "b": "False",
            "c": "Maybe",
            "d": "None"
        },
        "correct_answer": "a",
        "explanation": "This is a system-generated placeholder to prevent app crash on empty subcategories."
    },
    {
        "subject": "Environmental Engineering",
        "subcategory": "Sources & Demand of water",
        "type": "Theory-based MCQ",
        "question": "Sample placeholder question for Sources & Demand of water. [Set Variant 14]",
        "options": {
            "a": "True",
            "b": "False",
            "c": "Maybe",
            "d": "None"
        },
        "correct_answer": "a",
        "explanation": "This is a system-generated placeholder to prevent app crash on empty subcategories."
    },
    {
        "subject": "Environmental Engineering",
        "subcategory": "Sources & Demand of water",
        "type": "Theory-based MCQ",
        "question": "Sample placeholder question for Sources & Demand of water. [Set Variant 15]",
        "options": {
            "a": "True",
            "b": "False",
            "c": "Maybe",
            "d": "None"
        },
        "correct_answer": "a",
        "explanation": "This is a system-generated placeholder to prevent app crash on empty subcategories."
    },
    {
        "subject": "Environmental Engineering",
        "subcategory": "Sources & Demand of water",
        "type": "Theory-based MCQ",
        "question": "Sample placeholder question for Sources & Demand of water. [Set Variant 16]",
        "options": {
            "a": "True",
            "b": "False",
            "c": "Maybe",
            "d": "None"
        },
        "correct_answer": "a",
        "explanation": "This is a system-generated placeholder to prevent app crash on empty subcategories."
    },
    {
        "subject": "Environmental Engineering",
        "subcategory": "Sources & Demand of water",
        "type": "Theory-based MCQ",
        "question": "Sample placeholder question for Sources & Demand of water. [Set Variant 17]",
        "options": {
            "a": "True",
            "b": "False",
            "c": "Maybe",
            "d": "None"
        },
        "correct_answer": "a",
        "explanation": "This is a system-generated placeholder to prevent app crash on empty subcategories."
    },
    {
        "subject": "Environmental Engineering",
        "subcategory": "Sources & Demand of water",
        "type": "Theory-based MCQ",
        "question": "Sample placeholder question for Sources & Demand of water. [Set Variant 18]",
        "options": {
            "a": "True",
            "b": "False",
            "c": "Maybe",
            "d": "None"
        },
        "correct_answer": "a",
        "explanation": "This is a system-generated placeholder to prevent app crash on empty subcategories."
    },
    {
        "subject": "Environmental Engineering",
        "subcategory": "Sources & Demand of water",
        "type": "Theory-based MCQ",
        "question": "Sample placeholder question for Sources & Demand of water. [Set Variant 19]",
        "options": {
            "a": "True",
            "b": "False",
            "c": "Maybe",
            "d": "None"
        },
        "correct_answer": "a",
        "explanation": "This is a system-generated placeholder to prevent app crash on empty subcategories."
    },
    {
        "subject": "Environmental Engineering",
        "subcategory": "Sources & Demand of water",
        "type": "Theory-based MCQ",
        "question": "Sample placeholder question for Sources & Demand of water. [Set Variant 20]",
        "options": {
            "a": "True",
            "b": "False",
            "c": "Maybe",
            "d": "None"
        },
        "correct_answer": "a",
        "explanation": "This is a system-generated placeholder to prevent app crash on empty subcategories."
    },
    {
        "subject": "Environmental Engineering",
        "subcategory": "Sources & Demand of water",
        "type": "Theory-based MCQ",
        "question": "Sample placeholder question for Sources & Demand of water. [Set Variant 21]",
        "options": {
            "a": "True",
            "b": "False",
            "c": "Maybe",
            "d": "None"
        },
        "correct_answer": "a",
        "explanation": "This is a system-generated placeholder to prevent app crash on empty subcategories."
    },
    {
        "subject": "Environmental Engineering",
        "subcategory": "Sources & Demand of water",
        "type": "Theory-based MCQ",
        "question": "Sample placeholder question for Sources & Demand of water. [Set Variant 22]",
        "options": {
            "a": "True",
            "b": "False",
            "c": "Maybe",
            "d": "None"
        },
        "correct_answer": "a",
        "explanation": "This is a system-generated placeholder to prevent app crash on empty subcategories."
    },
    {
        "subject": "Environmental Engineering",
        "subcategory": "Sources & Demand of water",
        "type": "Theory-based MCQ",
        "question": "Sample placeholder question for Sources & Demand of water. [Set Variant 23]",
        "options": {
            "a": "True",
            "b": "False",
            "c": "Maybe",
            "d": "None"
        },
        "correct_answer": "a",
        "explanation": "This is a system-generated placeholder to prevent app crash on empty subcategories."
    },
    {
        "subject": "Environmental Engineering",
        "subcategory": "Sources & Demand of water",
        "type": "Theory-based MCQ",
        "question": "Sample placeholder question for Sources & Demand of water. [Set Variant 24]",
        "options": {
            "a": "True",
            "b": "False",
            "c": "Maybe",
            "d": "None"
        },
        "correct_answer": "a",
        "explanation": "This is a system-generated placeholder to prevent app crash on empty subcategories."
    }
]